RsLogMod/__init__.py
RsLogMod/rlog.py
RsLogMod/bin/__init__.py
RsLogMod/bin/dictionaries.py
RsLogMod/bin/rslogmod.py
RsLogMod/bin/utils.py
RsLogMod/configs/configs.json
rslogmod-1.3.0.dist-info/licenses/LICENSE
rslogmod-1.3.0.dist-info/METADATA
rslogmod-1.3.0.dist-info/WHEEL
rslogmod-1.3.0.dist-info/top_level.txt
rslogmod-1.3.0.dist-info/RECORD
