Metadata-Version: 2.4
Name: RsLogMod
Version: 1.3.0
Summary: A versatile logging module for Python projects
Home-page: https://github.com/D-3-X/RsLogMod/
Author: D-3-X
Author-email: felix.dxlan@gmail.com
License: MIT
Project-URL: Bug Tracker, https://github.com/D-3-X/RsLogMod/issues
Project-URL: Documentation, https://github.com/D-3-X/RsLogMod#readme
Project-URL: Source Code, https://github.com/D-3-X/RsLogMod
Keywords: logging,log rotation,python logging,programmable customization
Classifier: Programming Language :: Python :: 3
Classifier: License :: OSI Approved :: MIT License
Classifier: Operating System :: OS Independent
Requires-Python: >=3.6
License-File: LICENSE
Dynamic: author
Dynamic: author-email
Dynamic: classifier
Dynamic: description
Dynamic: description-content-type
Dynamic: home-page
Dynamic: keywords
Dynamic: license
Dynamic: license-file
Dynamic: project-url
Dynamic: requires-python
Dynamic: summary
